MANIFEST.in
README.rst
setup.cfg
setup.py
activitystream/__init__.py
activitystream/bootstrap.py
activitystream/helpers.py
activitystream/partials.py
activitystream/controllers/__init__.py
activitystream/controllers/root.py
activitystream/i18n/activitystream.pot
activitystream/i18n/it/LC_MESSAGES/activitystream.mo
activitystream/i18n/it/LC_MESSAGES/activitystream.po
activitystream/i18n/ru/LC_MESSAGES/activitystream.mo
activitystream/i18n/ru/LC_MESSAGES/activitystream.po
activitystream/lib/__init__.py
activitystream/lib/managers.py
activitystream/model/__init__.py
activitystream/model/ming_models.py
activitystream/public/__init__.py
activitystream/public/css/style.css
activitystream/public/images/star.png
activitystream/templates/__init__.py
activitystream/templates/index.xhtml
activitystream/templates/partials/__init__.py
activitystream/templates/partials/bootstrap_widget.xhtml
tgapp_activitystream.egg-info/PKG-INFO
tgapp_activitystream.egg-info/SOURCES.txt
tgapp_activitystream.egg-info/dependency_links.txt
tgapp_activitystream.egg-info/entry_points.txt
tgapp_activitystream.egg-info/not-zip-safe
tgapp_activitystream.egg-info/requires.txt
tgapp_activitystream.egg-info/top_level.txt