Metadata-Version: 1.0
Name: tgapp-activitystream
Version: 0.1.1
Summary: Pluggable for create a simple activity stream.
Home-page: https://github.com/axant/tgapp-activitystream
Author: AXANT
Author-email: tech@axant.it
License: UNKNOWN
Keywords: turbogears2.application
Platform: UNKNOWN
